trustpilotreviews/.gitignore
trustpilotreviews/__init__.py
trustpilotreviews/example.py
trustpilotreviews/get_reviews.py
trustpilotreviews-0.1.2.dist-info/LICENSE
trustpilotreviews-0.1.2.dist-info/WHEEL
trustpilotreviews-0.1.2.dist-info/METADATA
trustpilotreviews-0.1.2.dist-info/RECORD
