Metadata-Version: 2.1
Name: trustpilotreviews
Version: 0.1.2
Summary: Unoffice TrustPilot API to download reviews scores and contents
Home-page: https://github.com/Proteusiq/TrustPilotReader
Author: Prayson Wilfred Daniel
Author-email: praysonwilfred@gmail.com
Requires-Python: >=3.6,<4.0
Classifier: Intended Audience :: Developers
Classifier: License :: OSI Approved :: BSD License
Classifier: Programming Language :: Python :: 3
Classifier: Programming Language :: Python :: 3.6
Classifier: Programming Language :: Python :: 3.7
Classifier: Topic :: Software Development :: Libraries :: Python Modules
Requires-Dist: dataset (>=1.1,<2.0)
Requires-Dist: numpy (>=1.15,<2.0)
Requires-Dist: pandas (>=0.23.0,<0.24.0)
Requires-Dist: requests (>=2.20,<3.0)
Requires-Dist: stuf (>=0.9.16,<0.10.0)
Requires-Dist: tqdm (>=4.32,<5.0)
Project-URL: Repository, https://github.com/Proteusiq/TrustPilotReader
